AUTHORS.rst
CHANGELOG.rst
LICENSE
MANIFEST.in
README.rst
setup.py
football/__init__.py
football/admin.py
football/decorators.py
football/models.py
football/urls.py
football/urls_basic.py
football/urls_web.py
football/views.py
football/fixtures/photosizes.json
football/locale/fr/LC_MESSAGES/django.mo
football/locale/fr/LC_MESSAGES/django.po
football/management/__init__.py
football/management/commands/__init__.py
football/management/commands/football_fetch.py
football/management/commands/football_fetch.py~
football/management/commands/football_live_scores.py
football/migrations/0002_initial.py
football/migrations/0003_auto__add_field_team_abbreviated_title.py
football/migrations/__init__.py
football/static/stub.txt
football/templates/basic/football/league_dashboard.html
football/templates/basic/football/league_fixtures.html
football/templates/basic/football/league_logs.html
football/templates/basic/football/league_results.html
football/templates/basic/football/live_scores.html
football/templates/basic/football/team_dashboard.html
football/templates/basic/football/team_players.html
football/templates/basic/football/inclusion_tags/league_detail.html
football/templates/basic/football/inclusion_tags/live_scores.html
football/templates/basic/football/inclusion_tags/player_detail.html
football/templates/basic/football/inclusion_tags/player_list_item_ipod.html
football/templates/basic/football/inclusion_tags/team_detail.html
football/templates/basic/football/inclusion_tags/trivia_list_item.html
football/templates/web/football/league_dashboard.html
football/templates/web/football/league_fixtures_widget.html
football/templates/web/football/league_galleries.html
football/templates/web/football/league_logs_widget.html
football/templates/web/football/league_posts.html
football/templates/web/football/league_results_widget.html
football/templates/web/football/more_leagues_menu_ajax.html
football/templates/web/football/team_dashboard.html
jmbo_football.egg-info/PKG-INFO
jmbo_football.egg-info/SOURCES.txt
jmbo_football.egg-info/dependency_links.txt
jmbo_football.egg-info/not-zip-safe
jmbo_football.egg-info/requires.txt
jmbo_football.egg-info/top_level.txt